{
    "name": "Akuma",
    "image": "images/akuma.png",
    "type": "enemy",
    "hp": 1500,
    "currentHp": 1500,
    "abilities": [
        {
            "name": "Q",
            "description": "Deals 500 damage",
            "type": "damage_player",
            "damage": 500,
            "castTime": 0.2,
            "cooldown": 3,
            "icon": "images/abilities/akuma_q.png"
        },
        {
            "name": "W",
            "description": "Self-buff Evade for 1s (can't take damage)",
            "type": "buff_evade",
            "buff": {
                "type": "evade",
                "duration": 1
            },
            "castTime": 0,
            "cooldown": 12,
            "icon": "images/abilities/akuma_w.png"
        },
        {
            "name": "E",
            "description": "Self-buff: Powers up your damage by 300% for 2s",
            "type": "buff_damage",
            "buff": {
                "type": "damage",
                "multiplier": 3,
                "duration": 2
            },
            "castTime": 0,
            "cooldown": 22,
            "icon": "images/abilities/akuma_e.png"
        },
        {
            "name": "R",
            "description": "Stuns the enemy for 5s",
            "type": "stun_enemy",
            "debuff": {
                "type": "stun",
                "duration": 5
            },
            "castTime": 1,
            "cooldown": 35,
            "icon": "images/abilities/akuma_r.png"
        }
    ]
}
